keras_dna/__init__.py
keras_dna/evaluation.py
keras_dna/extractors.py
keras_dna/generators.py
keras_dna/hyperparams.py
keras_dna/keras_utils.py
keras_dna/kernel_analysis.py
keras_dna/layers.py
keras_dna/model.py
keras_dna/normalization.py
keras_dna/sequence.py
keras_dna/utils.py
keras_dna-0.0.46.dist-info/LICENSE
keras_dna-0.0.46.dist-info/METADATA
keras_dna-0.0.46.dist-info/WHEEL
keras_dna-0.0.46.dist-info/top_level.txt
keras_dna-0.0.46.dist-info/RECORD
