Metadata-Version: 2.1
Name: keras-dna
Version: 0.0.46
Summary: Build keras generator for genomic application
Home-page: https://github.com/etirouthier/keras_dna
Author: Etienne Routhier
Author-email: etienne.routhier@upmc.fr
License: MIT
Platform: UNKNOWN
Classifier: License :: OSI Approved :: MIT License
Classifier: Programming Language :: Python :: 3
Classifier: Programming Language :: Python :: 3.6
Requires-Dist: tensorflow (>=2.0.0)
Requires-Dist: numpy
Requires-Dist: pandas
Requires-Dist: kipoiseq
Requires-Dist: pyBigWig
Requires-Dist: pybedtools
